ibm_watson_studio_pipelines/__init__.py
ibm_watson_studio_pipelines/_client_errors.py
ibm_watson_studio_pipelines/_cpd_paths.py
ibm_watson_studio_pipelines/_cpd_paths_base.py
ibm_watson_studio_pipelines/client.py
ibm_watson_studio_pipelines/client_errors.py
ibm_watson_studio_pipelines/cpd_paths.py
ibm_watson_studio_pipelines/utils.py
ibm_watson_studio_pipelines/version.py
ibm_watson_studio_pipelines-0.2.12.dist-info/LICENSE
ibm_watson_studio_pipelines-0.2.12.dist-info/METADATA
ibm_watson_studio_pipelines-0.2.12.dist-info/WHEEL
ibm_watson_studio_pipelines-0.2.12.dist-info/top_level.txt
ibm_watson_studio_pipelines-0.2.12.dist-info/RECORD
