Metadata-Version: 2.1
Name: ibm-watson-studio-pipelines
Version: 0.2.12
Summary: Python utilities for IBM Watson Studio Pipelines
Home-page: https://github.ibm.com/AILifecycle/ibm-watson-studio-pipelines
Author: Michalina Kotwica
Author-email: michalina.kotwica@ibm.com
Classifier: Programming Language :: Python :: 3
Classifier: License :: OSI Approved :: MIT License
Classifier: Operating System :: OS Independent
Requires-Python: >=3.7
License-File: LICENSE
Requires-Dist: ibm-cloud-sdk-core (>=3.11.3)
Requires-Dist: ibm-cos-sdk (>=2.10.0)
Requires-Dist: attrs (>=21.2.0)
Requires-Dist: requests (>=2.25.1)
Requires-Dist: responses (>=0.13.4)
Requires-Dist: pytest (>=6.2.5)
Requires-Dist: typing-extensions (>=3.7.4)
